iec62056_21_dzg/__init__.py
iec62056_21_dzg/client.py
iec62056_21_dzg/constants.py
iec62056_21_dzg/exceptions.py
iec62056_21_dzg/lis200.py
iec62056_21_dzg/messages.py
iec62056_21_dzg/transports.py
iec62056_21_dzg/utils.py
iec62056_21_dzg-0.0.4.dist-info/METADATA
iec62056_21_dzg-0.0.4.dist-info/WHEEL
iec62056_21_dzg-0.0.4.dist-info/licenses/LICENSE.txt
iec62056_21_dzg-0.0.4.dist-info/RECORD
