Metadata-Version: 2.3
Name: iec62056-21_dzg
Version: 0.0.4
Summary: A Python library for IEC62056-21, Local Data Readout of Energy Meters, specialy DZG. Former IEC1107
Project-URL: Homepage, https://github.com/pwitab/iec62056-21
Project-URL: Issues, https://github.com/pwitab/iec62056-21/issues
Author-email: Henrik Palmlund Wahlgren <ralph@vukee.com>
License-File: LICENSE.txt
Classifier: License :: OSI Approved :: MIT License
Classifier: Operating System :: OS Independent
Classifier: Programming Language :: Python :: 3
Requires-Python: >=3.6
